setup.py
tensor/__init__.py
tensor/aggregators.py
tensor/interfaces.py
tensor/objects.py
tensor/service.py
tensor/utils.py
tensor.egg-info/PKG-INFO
tensor.egg-info/SOURCES.txt
tensor.egg-info/dependency_links.txt
tensor.egg-info/requires.txt
tensor.egg-info/top_level.txt
tensor/ihateprotobuf/__init__.py
tensor/ihateprotobuf/proto_pb2.py
tensor/logs/__init__.py
tensor/logs/follower.py
tensor/logs/parsers.py
tensor/outputs/__init__.py
tensor/outputs/elasticsearch.py
tensor/outputs/riemann.py
tensor/protocol/__init__.py
tensor/protocol/elasticsearch.py
tensor/protocol/icmp.py
tensor/protocol/riemann.py
tensor/protocol/sflow/__init__.py
tensor/protocol/sflow/server.py
tensor/protocol/sflow/protocol/__init__.py
tensor/protocol/sflow/protocol/counters.py
tensor/protocol/sflow/protocol/flows.py
tensor/protocol/sflow/protocol/protocol.py
tensor/protocol/sflow/protocol/utils.py
tensor/sources/__init__.py
tensor/sources/docker.py
tensor/sources/generator.py
tensor/sources/haproxy.py
tensor/sources/munin.py
tensor/sources/network.py
tensor/sources/nginx.py
tensor/sources/rabbitmq.py
tensor/sources/redis.py
tensor/sources/riak.py
tensor/sources/riemann.py
tensor/sources/sflow.py
tensor/sources/snmp.py
tensor/sources/database/__init__.py
tensor/sources/database/elasticsearch.py
tensor/sources/database/memcache.py
tensor/sources/database/postgresql.py
tensor/sources/linux/__init__.py
tensor/sources/linux/basic.py
tensor/sources/linux/ipsec.py
tensor/sources/linux/process.py
tensor/sources/linux/sensors.py
tensor/sources/media/__init__.py
tensor/sources/media/libav.py
tensor/sources/python/__init__.py
tensor/sources/python/uwsgi.py
tensor/tests/__init__.py
tensor/tests/test_logs.py
tensor/tests/test_service.py
tensor/tests/test_sflow.py
tensor/tests/test_sources.py
tensor/tests/test_tensor.py
tensor/tests/test_utils.py
twisted/plugins/tensor_plugin.py