Metadata-Version: 1.1
Name: tensor
Version: 0.3.5
Summary: A Twisted based monitoring agent for Riemann
Home-page: http://github.com/calston/tensor
Author: Colin Alston
Author-email: colin.alston@gmail.com
License: MIT
Platform: UNKNOWN
Classifier: Development Status :: 4 - Beta
Classifier: Intended Audience :: System Administrators
Classifier: License :: OSI Approved :: MIT License
Classifier: Operating System :: POSIX
Classifier: Programming Language :: Python
Classifier: Topic :: System :: Monitoring
